llm_bot/__init__.py
llm_bot/core.py
llm_bot-0.1.3.dist-info/LICENSE
llm_bot-0.1.3.dist-info/METADATA
llm_bot-0.1.3.dist-info/WHEEL
llm_bot-0.1.3.dist-info/entry_points.txt
llm_bot-0.1.3.dist-info/RECORD
